suap_xlrd-1.1.1.data/scripts/runxlrd.py
xlrd/__init__.py
xlrd/biffh.py
xlrd/book.py
xlrd/compdoc.py
xlrd/formatting.py
xlrd/formula.py
xlrd/info.py
xlrd/sheet.py
xlrd/timemachine.py
xlrd/xldate.py
xlrd/xlsx.py
xlrd/examples/namesdemo.xls
xlrd/examples/xlrdnameAPIdemo.py
suap_xlrd-1.1.1.dist-info/METADATA
suap_xlrd-1.1.1.dist-info/WHEEL
suap_xlrd-1.1.1.dist-info/top_level.txt
suap_xlrd-1.1.1.dist-info/RECORD
